contiguous/__init__.py
contiguous/structures.py
tests/__init__.py
tests/test-contiguous.py
contiguous-0.0.1.dist-info/LICENSE
contiguous-0.0.1.dist-info/METADATA
contiguous-0.0.1.dist-info/WHEEL
contiguous-0.0.1.dist-info/top_level.txt
contiguous-0.0.1.dist-info/RECORD
